crazy_hamster
