Metadata-Version: 1.0
Name: crazy-hamster
Version: 0.3
Summary: The craziest hamster in the world
Home-page: https://github.com/ehsangolshani/crazy-hamster
Author: Ehsan Golshani
Author-email: ehsanroman74@gmail.com
License: GNU
Platform: UNKNOWN
